<?xml version="1.0" encoding="UTF-8"?>
<!DOCTYPE mapper PUBLIC "-//mybatis.org//DTD Mapper 3.0//EN" "http://mybatis.org/dtd/mybatis-3-mapper.dtd">
<mapper namespace="home.helper.batch.persistence.database.v1.table.DbV1HelperKidParentMapper">
    <resultMap id="BaseResultMap" type="home.helper.batch.persistence.database.v1.table.DbV1HelperKidParent">
        <!--
          WARNING - @mbg.generated
          This element is automatically generated by MyBatis Generator, do not modify.
        -->
        <id column="helper_kid_parent_id" jdbcType="VARCHAR" property="helperKidParentId"/>
        <result column="helper_kid_id" jdbcType="VARCHAR" property="helperKidId"/>
        <result column="parent_user_id" jdbcType="VARCHAR" property="parentUserId"/>
    </resultMap>
    <sql id="Base_Column_List">
        <!--
          WARNING - @mbg.generated
          This element is automatically generated by MyBatis Generator, do not modify.
        -->
        helper_kid_parent_id, helper_kid_id, parent_user_id
    </sql>
    <select id="selectByPrimaryKey" parameterType="java.lang.String" resultMap="BaseResultMap">
        <!--
          WARNING - @mbg.generated
          This element is automatically generated by MyBatis Generator, do not modify.
        -->
        select
        <include refid="Base_Column_List"/>
        from helper_kids.helper_kid_parent
        where helper_kid_parent_id = #{helperKidParentId,jdbcType=VARCHAR}
    </select>
    <delete id="deleteByPrimaryKey" parameterType="java.lang.String">
        <!--
          WARNING - @mbg.generated
          This element is automatically generated by MyBatis Generator, do not modify.
        -->
        delete from helper_kids.helper_kid_parent
        where helper_kid_parent_id = #{helperKidParentId,jdbcType=VARCHAR}
    </delete>
    <insert id="insert" parameterType="home.helper.batch.persistence.database.v1.table.DbV1HelperKidParent">
        <!--
          WARNING - @mbg.generated
          This element is automatically generated by MyBatis Generator, do not modify.
        -->
        insert into helper_kids.helper_kid_parent (helper_kid_parent_id, helper_kid_id, parent_user_id
        )
        values (#{helperKidParentId,jdbcType=VARCHAR}, #{helperKidId,jdbcType=VARCHAR}, #{parentUserId,jdbcType=VARCHAR}
        )
    </insert>
    <insert id="insertSelective" parameterType="home.helper.batch.persistence.database.v1.table.DbV1HelperKidParent">
        <!--
          WARNING - @mbg.generated
          This element is automatically generated by MyBatis Generator, do not modify.
        -->
        insert into helper_kids.helper_kid_parent
        <trim prefix="(" suffix=")" suffixOverrides=",">
            <if test="helperKidParentId != null">
                helper_kid_parent_id,
            </if>
            <if test="helperKidId != null">
                helper_kid_id,
            </if>
            <if test="parentUserId != null">
                parent_user_id,
            </if>
        </trim>
        <trim prefix="values (" suffix=")" suffixOverrides=",">
            <if test="helperKidParentId != null">
                #{helperKidParentId,jdbcType=VARCHAR},
            </if>
            <if test="helperKidId != null">
                #{helperKidId,jdbcType=VARCHAR},
            </if>
            <if test="parentUserId != null">
                #{parentUserId,jdbcType=VARCHAR},
            </if>
        </trim>
    </insert>
    <update id="updateByPrimaryKeySelective"
            parameterType="home.helper.batch.persistence.database.v1.table.DbV1HelperKidParent">
        <!--
          WARNING - @mbg.generated
          This element is automatically generated by MyBatis Generator, do not modify.
        -->
        update helper_kids.helper_kid_parent
        <set>
            <if test="helperKidId != null">
                helper_kid_id = #{helperKidId,jdbcType=VARCHAR},
            </if>
            <if test="parentUserId != null">
                parent_user_id = #{parentUserId,jdbcType=VARCHAR},
            </if>
        </set>
        where helper_kid_parent_id = #{helperKidParentId,jdbcType=VARCHAR}
    </update>
    <update id="updateByPrimaryKey" parameterType="home.helper.batch.persistence.database.v1.table.DbV1HelperKidParent">
        <!--
          WARNING - @mbg.generated
          This element is automatically generated by MyBatis Generator, do not modify.
        -->
        update helper_kids.helper_kid_parent
        set helper_kid_id = #{helperKidId,jdbcType=VARCHAR},
        parent_user_id = #{parentUserId,jdbcType=VARCHAR}
        where helper_kid_parent_id = #{helperKidParentId,jdbcType=VARCHAR}
    </update>
</mapper>